{
  "igpTeamId" : 410754,
  "igpManagerId" : 410746,
  "teamName" : "Tushek Eslovenia F1",
  "nationality" : "gb",
  "color" : "#d1be00",
  "carImage" : "https://igpmanager.azureedge.net/igp/livery/410754s.png?1560204586",
  "drivers" : [ 5789426, 4916681 ],
  "totalPoints" : 0,
  "wins" : 0,
  "poles" : 0,
  "podiums" : 0,
  "topTens" : 0,
  "fastestLaps" : 0,
  "participations" : 0,
  "finishedRaces" : 0,
  "dnfs" : 0,
  "stats" : {
    "id" : 42,
    "championships" : 0,
    "points" : 0,
    "wins" : 0,
    "poles" : 0,
    "podiums" : 0,
    "topTens" : 0,
    "fastestLaps" : 0,
    "participations" : 0,
    "finishedRaces" : 0
  },
  "eventsPoints" : {
    "AUSTRALIA" : 0
  }
}