{
  "igpDriverId" : 5398423,
  "driverName" : "Raiquen Flores",
  "nationality" : "ar",
  "color" : "#ff1f00",
  "igpTeamId" : 757134,
  "teamName" : "Yañez Team",
  "totalPoints" : 25,
  "wins" : 0,
  "poles" : 0,
  "podiums" : 1,
  "topTens" : 2,
  "fastestLaps" : 0,
  "participations" : 2,
  "finishedRaces" : 0,
  "dnfs" : 0,
  "stats" : {
    "id" : 70,
    "championships" : 0,
    "points" : 0,
    "wins" : 0,
    "poles" : 0,
    "podiums" : 0,
    "topTens" : 0,
    "fastestLaps" : 0,
    "participations" : 0,
    "finishedRaces" : 0
  },
  "eventsPositions" : {
    "MALAYSIA" : 5,
    "AUSTRALIA" : 3
  },
  "eventsPoints" : {
    "MALAYSIA" : 10,
    "AUSTRALIA" : 15
  }
}