{
  "igpTeamId" : 420884,
  "igpManagerId" : 420876,
  "teamName" : "Garmex",
  "nationality" : "mx",
  "color" : "#4a8ae5",
  "carImage" : "https://igpmanager.azureedge.net/igp/livery/420884s.png?1506972046",
  "drivers" : [ 7571380, 4137184, 3972973 ],
  "totalPoints" : 0,
  "wins" : 0,
  "poles" : 0,
  "podiums" : 0,
  "topTens" : 0,
  "fastestLaps" : 0,
  "participations" : 4,
  "finishedRaces" : 0,
  "dnfs" : 0,
  "stats" : {
    "id" : 42,
    "championships" : 0,
    "points" : 0,
    "wins" : 0,
    "poles" : 0,
    "podiums" : 0,
    "topTens" : 0,
    "fastestLaps" : 0,
    "participations" : 0,
    "finishedRaces" : 0
  },
  "eventsPoints" : {
    "AUSTRALIA" : 0,
    "MALAYSIA" : 0
  }
}