{
  "igpTeamId" : 337354,
  "igpManagerId" : 337346,
  "teamName" : "GnomoTeam",
  "nationality" : "es",
  "color" : "#08f034",
  "carImage" : "https://igpmanager.azureedge.net/igp/livery/337354s.png?1542732829",
  "drivers" : [ 5177590, 5182678, 7408800 ],
  "totalPoints" : 31,
  "wins" : 0,
  "poles" : 0,
  "podiums" : 3,
  "topTens" : 8,
  "fastestLaps" : 3,
  "participations" : 8,
  "finishedRaces" : 0,
  "dnfs" : 0,
  "stats" : {
    "id" : 34,
    "championships" : 0,
    "points" : 0,
    "wins" : 0,
    "poles" : 0,
    "podiums" : 0,
    "topTens" : 0,
    "fastestLaps" : 0,
    "participations" : 0,
    "finishedRaces" : 0
  },
  "eventsPoints" : {
    "AUSTRALIA" : 23,
    "MALAYSIA" : 8
  }
}