{
  "igpTeamId" : 805991,
  "igpManagerId" : 805984,
  "teamName" : "Opettaja EricDeath F1",
  "nationality" : "fi",
  "color" : "#00fffa",
  "carImage" : "https://igpmanager.azureedge.net/igp/livery/805991s.png?1539180084",
  "drivers" : [ 5205880, 5071337 ],
  "totalPoints" : 282,
  "wins" : 6,
  "poles" : 2,
  "podiums" : 13,
  "topTens" : 14,
  "fastestLaps" : 3,
  "participations" : 14,
  "finishedRaces" : 0,
  "dnfs" : 0,
  "stats" : {
    "id" : 40,
    "championships" : 0,
    "points" : 0,
    "wins" : 0,
    "poles" : 0,
    "podiums" : 0,
    "topTens" : 0,
    "fastestLaps" : 0,
    "participations" : 0,
    "finishedRaces" : 0
  },
  "eventsPoints" : {
    "SPAIN" : 43,
    "CHINA" : 43,
    "MALAYSIA" : 43,
    "TURKEY" : 43,
    "MONACO" : 33,
    "AUSTRALIA" : 37,
    "BAHRAIN" : 40
  }
}