{
  "igpDriverId" : 7219583,
  "driverName" : "Yerimen Torres",
  "nationality" : "ar",
  "color" : "#66cccc",
  "igpTeamId" : 1710658,
  "teamName" : "Mortal",
  "totalPoints" : 1,
  "wins" : 0,
  "poles" : 0,
  "podiums" : 0,
  "topTens" : 1,
  "fastestLaps" : 0,
  "participations" : 1,
  "finishedRaces" : 0,
  "dnfs" : 0,
  "stats" : {
    "id" : 18,
    "championships" : 0,
    "points" : 0,
    "wins" : 0,
    "poles" : 0,
    "podiums" : 0,
    "topTens" : 0,
    "fastestLaps" : 0,
    "participations" : 0,
    "finishedRaces" : 0
  },
  "eventsPositions" : {
    "MALAYSIA" : 10
  },
  "eventsPoints" : {
    "MALAYSIA" : 1
  }
}